pypj/__init__.py
pypj/args.py
pypj/const.py
pypj/cui.py
pypj/environment.py
pypj/exception.py
pypj/file_path.py
pypj/main.py
pypj/resource.py
pypj/resources/.pre-commit-config.yaml
pypj/resources/Makefile
pypj/resources/Makefile_precommit
pypj/resources/README.md
pypj/resources/dependabot.yml
pypj/resources/package/init.py
pypj/resources/package/test_package.py
pypj/resources/publish.yml
pypj/resources/settings.jsonc
pypj/resources/unittest.yml
pypj/setting.py
pypj/task/__init__.py
pypj/task/githubactions.py
pypj/task/makefile.py
pypj/task/poetry.py
pypj/task/precommit.py
pypj/task/pyproject.py
pypj/task/readme.py
pypj/task/task.py
pypj/task/task_manager.py
pypj/task/vscode.py
pypj/type_def.py
pypj-1.2.0.dist-info/entry_points.txt
pypj-1.2.0.dist-info/METADATA
pypj-1.2.0.dist-info/LICENSE
pypj-1.2.0.dist-info/WHEEL
pypj-1.2.0.dist-info/RECORD
