Metadata-Version: 2.1
Name: pypj
Version: 1.2.0
Summary: Python project initializer
Home-page: https://github.com/edge-minato/pypj
License: MIT
Keywords: packaging,developent,environment,poetry
Author: edge-minato
Author-email: edge.minato@gmail.com
Requires-Python: >=3.8,<4.0
Classifier: Development Status :: 4 - Beta
Classifier: Environment :: Console
Classifier: Intended Audience :: Developers
Classifier: License :: OSI Approved :: MIT License
Classifier: Operating System :: Unix
Classifier: Programming Language :: Python :: 3
Classifier: Programming Language :: Python :: 3.8
Classifier: Programming Language :: Python :: 3.9
Classifier: Programming Language :: Python :: 3.10
Classifier: Programming Language :: Python :: 3.11
Classifier: Programming Language :: Python :: 3.10
Classifier: Programming Language :: Python :: 3.8
Classifier: Programming Language :: Python :: 3.9
Classifier: Topic :: Software Development :: Libraries :: Python Modules
Requires-Dist: single-source (>=0.2,<0.4)
Project-URL: Repository, https://github.com/edge-minato/pypj
